{"otherData": {},"traceEvents":[{},{"cat":"function","dur":554,"name":"void Engine::ImGuiLayer::OnDetach(void)","ph":"X","pid":0,"tid":19596,"ts":1445216910143.500},{"cat":"function","dur":0,"name":"void Engine::EditorLayer::OnDetach(void)","ph":"X","pid":0,"tid":19596,"ts":1445216910749.400},{"cat":"function","dur":1,"name":"Engine::OpenGLTexture2D::~OpenGLTexture2D(void)","ph":"X","pid":0,"tid":19596,"ts":1445216910787.800},{"cat":"function","dur":0,"name":"Engine::OpenGLTexture2D::~OpenGLTexture2D(void)","ph":"X","pid":0,"tid":19596,"ts":1445216910821.100},{"cat":"function","dur":17304,"name":"void Engine::WindowsWindow::Shutdown(void)","ph":"X","pid":0,"tid":19596,"ts":1445216910910.700},{"cat":"function","dur":17806,"name":"Engine::WindowsWindow::~WindowsWindow(void)","ph":"X","pid":0,"tid":19596,"ts":1445216910910.600}]}