{"otherData": {},"traceEvents":[{},{"cat":"function","dur":16893,"name":"glfwInit","ph":"X","pid":0,"tid":19596,"ts":1445187180535.300},{"cat":"function","dur":138533,"name":"glfwCreateWindow","ph":"X","pid":0,"tid":19596,"ts":1445187197981.000},{"cat":"function","dur":1823,"name":"void Engine::OpenGLContext::Init(void)","ph":"X","pid":0,"tid":19596,"ts":1445187336806.700},{"cat":"function","dur":159038,"name":"void Engine::WindowsWindow::Init(const struct Engine::WindowProps &)","ph":"X","pid":0,"tid":19596,"ts":1445187179716.100},{"cat":"function","dur":159193,"name":"Engine::WindowsWindow::WindowsWindow(const struct Engine::WindowProps &)","ph":"X","pid":0,"tid":19596,"ts":1445187179713.700},{"cat":"function","dur":5,"name":"void Engine::OpenGLRendererAPI::Init(void)","ph":"X","pid":0,"tid":19596,"ts":1445187339083.000},{"cat":"function","dur":19,"name":"Engine::OpenGLVertexArray::OpenGLVertexArray(void)","ph":"X","pid":0,"tid":19596,"ts":1445187339159.700},{"cat":"function","dur":18,"name":"Engine::OpenGLVertexBuffer::OpenGLVertexBuffer(unsigned int)","ph":"X","pid":0,"tid":19596,"ts":1445187339252.800},{"cat":"function","dur":0,"name":"void Engine::OpenGLVertexBuffer::Bind(void) const","ph":"X","pid":0,"tid":19596,"ts":1445187339365.200},{"cat":"function","dur":76,"name":"void Engine::OpenGLVertexArray::AddVertexBuffer(const class std::shared_ptr<class Engine::VertexBuffer> &)","ph":"X","pid":0,"tid":19596,"ts":1445187339339.000},{"cat":"function","dur":21,"name":"Engine::OpenGLIndexBuffer::OpenGLIndexBuffer(unsigned int *,unsigned int)","ph":"X","pid":0,"tid":19596,"ts":1445187339518.700},{"cat":"function","dur":0,"name":"void Engine::OpenGLIndexBuffer::Bind(void) const","ph":"X","pid":0,"tid":19596,"ts":1445187339579.600},{"cat":"function","dur":112,"name":"Engine::OpenGLTexture2D::OpenGLTexture2D(unsigned int,unsigned int)","ph":"X","pid":0,"tid":19596,"ts":1445187339626.300},{"cat":"function","dur":6,"name":"void Engine::OpenGLTexture2D::SetData(void *,unsigned int)","ph":"X","pid":0,"tid":19596,"ts":1445187339780.600},{"cat":"function","dur":155,"name":"class std::basic_string<char,struct std::char_traits<char>,class std::allocator<char> > Engine::OpenGLShader::ReadFile(const class std::basic_string<char,struct std::char_traits<char>,class std::allocator<char> > &)","ph":"X","pid":0,"tid":19596,"ts":1445187339837.900},{"cat":"function","dur":685,"name":"void Engine::OpenGLShader::Compile(const class std::unordered_map<unsigned int,class std::basic_string<char,struct std::char_traits<char>,class std::allocator<char> >,struct std::hash<unsigned int>,struct std::equal_to<unsigned int>,class std::allocator<struct std::pair<unsigned int const ,class std::basic_string<char,struct std::char_traits<char>,class std::allocator<char> > > > > &)","ph":"X","pid":0,"tid":19596,"ts":1445187340103.400},{"cat":"function","dur":1069,"name":"Engine::OpenGLShader::OpenGLShader(const class std::basic_string<char,struct std::char_traits<char>,class std::allocator<char> > &)","ph":"X","pid":0,"tid":19596,"ts":1445187339834.700},{"cat":"function","dur":3,"name":"void Engine::OpenGLShader::Bind(void) const","ph":"X","pid":0,"tid":19596,"ts":1445187340941.900},{"cat":"function","dur":27,"name":"void Engine::OpenGLShader::SetIntArray(const class std::basic_string<char,struct std::char_traits<char>,class std::allocator<char> > &,int *,unsigned int)","ph":"X","pid":0,"tid":19596,"ts":1445187340979.000},{"cat":"function","dur":1901,"name":"void Engine::Renderer2D::Init(void)","ph":"X","pid":0,"tid":19596,"ts":1445187339142.300},{"cat":"function","dur":9,"name":"void Engine::LayerStack::PushLayer(class Engine::Layer *)","ph":"X","pid":0,"tid":19596,"ts":1445187341093.200},{"cat":"function","dur":909,"name":"void Engine::ImGuiLayer::OnAttach(void)","ph":"X","pid":0,"tid":19596,"ts":1445187341136.200},{"cat":"function","dur":162386,"name":"Engine::Application::Application(const class std::basic_string<char,struct std::char_traits<char>,class std::allocator<char> > &)","ph":"X","pid":0,"tid":19596,"ts":1445187179703.400},{"cat":"function","dur":39,"name":"void Engine::OrthographicCamera::RecalculateViewMatrix(void)","ph":"X","pid":0,"tid":19596,"ts":1445187342263.000},{"cat":"function","dur":3,"name":"void Engine::LayerStack::PushLayer(class Engine::Layer *)","ph":"X","pid":0,"tid":19596,"ts":1445187342402.500},{"cat":"function","dur":87412,"name":"OpenGLTexture2D::OpenGLTexture2D(const std::string& path) - stbi_load","ph":"X","pid":0,"tid":19596,"ts":1445187342452.400},{"cat":"function","dur":93333,"name":"Engine::OpenGLTexture2D::OpenGLTexture2D(const class std::basic_string<char,struct std::char_traits<char>,class std::allocator<char> > &)","ph":"X","pid":0,"tid":19596,"ts":1445187342449.400},{"cat":"function","dur":131820,"name":"OpenGLTexture2D::OpenGLTexture2D(const std::string& path) - stbi_load","ph":"X","pid":0,"tid":19596,"ts":1445187436092.300},{"cat":"function","dur":137561,"name":"Engine::OpenGLTexture2D::OpenGLTexture2D(const class std::basic_string<char,struct std::char_traits<char>,class std::allocator<char> > &)","ph":"X","pid":0,"tid":19596,"ts":1445187436092.000},{"cat":"function","dur":232452,"name":"void Engine::EditorLayer::OnAttach(void)","ph":"X","pid":0,"tid":19596,"ts":1445187342446.500}]}